basewhat/__init__.py
basewhat/basewhat.py
basewhat/py.typed
basewhat-1.1.1.dist-info/METADATA
basewhat-1.1.1.dist-info/WHEEL
basewhat-1.1.1.dist-info/RECORD
