Metadata-Version: 2.3
Name: basewhat
Version: 1.1.1
Summary: A Python utility for encoding/decoding arbitrary-base numbers.
License: MIT
Author: Paul Bissex
Author-email: paul@bissex.net
Requires-Python: >=3.6,<4.0
Classifier: Development Status :: 5 - Production/Stable
Classifier: License :: OSI Approved :: MIT License
Classifier: Programming Language :: Python
Classifier: Programming Language :: Python :: 3
Classifier: Programming Language :: Python :: 3.6
Classifier: Programming Language :: Python :: 3.7
Classifier: Programming Language :: Python :: 3.8
Classifier: Programming Language :: Python :: 3.9
Classifier: Programming Language :: Python :: 3.10
Classifier: Programming Language :: Python :: 3.11
Classifier: Programming Language :: Python :: 3.12
Classifier: Programming Language :: Python :: 3.13
Classifier: Topic :: Software Development :: Libraries :: Python Modules
Project-URL: Homepage, https://gitlab.com/paul_bissex/basewhat
Project-URL: Repository, https://gitlab.com/paul_bissex/basewhat/-/tree/trunk
